Metadata-Version: 2.1
Name: cda.ai-modular-framework
Version: 0.1.0
Summary: A modular AI framework
Home-page: https://github.com/Cdaprod/cda.ai-modular-framework
Author: Cdaprod
Author-email: Cdaprod@Cdaprod.dev
Classifier: Programming Language :: Python :: 3
Classifier: License :: OSI Approved :: MIT License
Classifier: Operating System :: OS Independent
Requires-Python: >=3.8
License-File: LICENSE.md
Requires-Dist: fastapi
Requires-Dist: uvicorn
Requires-Dist: python-dotenv
Requires-Dist: openai
Requires-Dist: kubernetes
Requires-Dist: pytest
Requires-Dist: flake8
